README.md
setup.cfg
setup.py
enaptorch/__init__.py
enaptorch/plotting.py
enaptorch/utils.py
enaptorch/version.py
enaptorch/warning_manager.py
enaptorch.egg-info/PKG-INFO
enaptorch.egg-info/SOURCES.txt
enaptorch.egg-info/dependency_links.txt
enaptorch.egg-info/requires.txt
enaptorch.egg-info/top_level.txt
enaptorch/framework/__init__.py
enaptorch/framework/experiment.py
enaptorch/framework/iterators.py
enaptorch/framework/model.py
enaptorch/framework/model_bundle.py
enaptorch/framework/optimizers.py
enaptorch/framework/callbacks/__init__.py
enaptorch/framework/callbacks/_utils.py
enaptorch/framework/callbacks/best_model_restore.py
enaptorch/framework/callbacks/callbacks.py
enaptorch/framework/callbacks/checkpoint.py
enaptorch/framework/callbacks/clip_grad.py
enaptorch/framework/callbacks/color_formatting.py
enaptorch/framework/callbacks/delay.py
enaptorch/framework/callbacks/earlystopping.py
enaptorch/framework/callbacks/gradient_logger.py
enaptorch/framework/callbacks/gradient_tracker.py
enaptorch/framework/callbacks/lambda_.py
enaptorch/framework/callbacks/logger.py
enaptorch/framework/callbacks/lr_scheduler.py
enaptorch/framework/callbacks/mlflow_logger.py
enaptorch/framework/callbacks/notification.py
enaptorch/framework/callbacks/periodic.py
enaptorch/framework/callbacks/policies.py
enaptorch/framework/callbacks/progress.py
enaptorch/framework/callbacks/progress_bar.py
enaptorch/framework/callbacks/terminate_on_nan.py
enaptorch/framework/callbacks/wandb_logger.py
enaptorch/framework/metrics/__init__.py
enaptorch/framework/metrics/base.py
enaptorch/framework/metrics/decomposable.py
enaptorch/framework/metrics/epoch_metrics.py
enaptorch/framework/metrics/metric_argument_indexing.py
enaptorch/framework/metrics/metrics_registering.py
enaptorch/framework/metrics/pytorch_loss_functions_registering.py
enaptorch/framework/metrics/utils.py
enaptorch/framework/metrics/predefined/__init__.py
enaptorch/framework/metrics/predefined/accuracy.py
enaptorch/framework/metrics/predefined/fscores.py
enaptorch/framework/metrics/predefined/sklearn_metrics.py
enaptorch/layers/__init__.py
enaptorch/layers/utils.py
tests/__init__.py
